pyusb_libusb1_backend/__init__.py
pyusb_libusb1_backend/libusb.cpython-39-x86_64-linux-gnu.so
pyusb_libusb1_backend.libs/libcap-79733b59.so.2.22
pyusb_libusb1_backend.libs/libudev-cbe9b76e.so.1.6.2
pyusb_libusb1_backend.libs/libelf-0-3d9de92a.176.so
pyusb_libusb1_backend.libs/libdw-0-780627ce.176.so
pyusb_libusb1_backend.libs/libattr-4f2a9577.so.1.1.0
pyusb_libusb1_backend.libs/libbz2-a273e504.so.1.0.6
pyusb_libusb1_backend.libs/liblzma-07b5b5c8.so.5.2.2
pyusb_libusb1_backend-0.0.1.dist-info/WHEEL
pyusb_libusb1_backend-0.0.1.dist-info/top_level.txt
pyusb_libusb1_backend-0.0.1.dist-info/METADATA
pyusb_libusb1_backend-0.0.1.dist-info/RECORD
